HISTORY.rst
LICENSE
MANIFEST.in
README.rst
setup.py
pytmux/__init__.py
pytmux/cli.py
pytmux/core.py
pytmux/schema.py
pytmux/utils.py
pytmux.egg-info/PKG-INFO
pytmux.egg-info/SOURCES.txt
pytmux.egg-info/dependency_links.txt
pytmux.egg-info/entry_points.txt
pytmux.egg-info/requires.txt
pytmux.egg-info/top_level.txt