Metadata-Version: 1.1
Name: pytmux
Version: 0.0.7
Summary: A simple wrapper for tmux.
Home-page: https://github.com/wraithan/pytmux
Author: Wraithan (Chris McDonald)
Author-email: xwraithanx@gmail.com
License: Apache License, Version 2.0
Platform: UNKNOWN
Classifier: Development Status :: 2 - Pre-Alpha
Classifier: Intended Audience :: Developers
Classifier: Natural Language :: English
Classifier: License :: OSI Approved :: Apache Software License
Classifier: Programming Language :: Python
Classifier: Programming Language :: Python :: 2.7
